{
  "page" : 0,
  "fullPageSize" : {
    "start" : {
      "x" : 0,
      "y" : 0
    },
    "end" : {
      "x" : 1133,
      "y" : 2014
    }
  },
  "pageSize" : null,
  "ayatPos" : [
    {
      "position" : {
        "center" : {
          "x" : 64,
          "y" : 781
        },
        "radius" : 28
      },
      "verseRef" : {
        "chapterNumber" : 7,
        "verseNumber" : 160
      }
    },
    {
      "position" : {
        "center" : {
          "x" : 64,
          "y" : 1128
        },
        "radius" : 28
      },
      "verseRef" : {
        "chapterNumber" : 7,
        "verseNumber" : 161
      }
    },
    {
      "position" : {
        "center" : {
          "x" : 806,
          "y" : 1477
        },
        "radius" : 28
      },
      "verseRef" : {
        "chapterNumber" : 7,
        "verseNumber" : 162
      }
    },
    {
      "position" : {
        "center" : {
          "x" : 63,
          "y" : 1821
        },
        "radius" : 28
      },
      "verseRef" : {
        "chapterNumber" : 7,
        "verseNumber" : 163
      }
    }
  ],
  "lines" : [
    {
      "start" : {
        "x" : 29,
        "y" : 142
      },
      "end" : {
        "x" : 1094,
        "y" : 257
      }
    },
    {
      "start" : {
        "x" : 29,
        "y" : 257
      },
      "end" : {
        "x" : 1094,
        "y" : 372
      }
    },
    {
      "start" : {
        "x" : 29,
        "y" : 372
      },
      "end" : {
        "x" : 1094,
        "y" : 487
      }
    },
    {
      "start" : {
        "x" : 29,
        "y" : 487
      },
      "end" : {
        "x" : 1094,
        "y" : 602
      }
    },
    {
      "start" : {
        "x" : 29,
        "y" : 602
      },
      "end" : {
        "x" : 1094,
        "y" : 717
      }
    },
    {
      "start" : {
        "x" : 29,
        "y" : 717
      },
      "end" : {
        "x" : 1094,
        "y" : 832
      }
    },
    {
      "start" : {
        "x" : 29,
        "y" : 832
      },
      "end" : {
        "x" : 1094,
        "y" : 947
      }
    },
    {
      "start" : {
        "x" : 29,
        "y" : 947
      },
      "end" : {
        "x" : 1094,
        "y" : 1062
      }
    },
    {
      "start" : {
        "x" : 29,
        "y" : 1062
      },
      "end" : {
        "x" : 1094,
        "y" : 1177
      }
    },
    {
      "start" : {
        "x" : 29,
        "y" : 1177
      },
      "end" : {
        "x" : 1094,
        "y" : 1292
      }
    },
    {
      "start" : {
        "x" : 29,
        "y" : 1292
      },
      "end" : {
        "x" : 1094,
        "y" : 1407
      }
    },
    {
      "start" : {
        "x" : 29,
        "y" : 1407
      },
      "end" : {
        "x" : 1094,
        "y" : 1533
      }
    },
    {
      "start" : {
        "x" : 29,
        "y" : 1533
      },
      "end" : {
        "x" : 1094,
        "y" : 1648
      }
    },
    {
      "start" : {
        "x" : 29,
        "y" : 1648
      },
      "end" : {
        "x" : 1094,
        "y" : 1763
      }
    },
    {
      "start" : {
        "x" : 29,
        "y" : 1763
      },
      "end" : {
        "x" : 1094,
        "y" : 1871
      }
    }
  ],
  "headers" : [ ],
  "basmallah" : [ ]
}