{
  "page" : 0,
  "fullPageSize" : {
    "start" : {
      "x" : 0,
      "y" : 0
    },
    "end" : {
      "x" : 1133,
      "y" : 2014
    }
  },
  "pageSize" : null,
  "ayatPos" : [
    {
      "position" : {
        "center" : {
          "x" : 571,
          "y" : 424
        },
        "radius" : 28
      },
      "verseRef" : {
        "chapterNumber" : 12,
        "verseNumber" : 23
      }
    },
    {
      "position" : {
        "center" : {
          "x" : 356,
          "y" : 656
        },
        "radius" : 28
      },
      "verseRef" : {
        "chapterNumber" : 12,
        "verseNumber" : 24
      }
    },
    {
      "position" : {
        "center" : {
          "x" : 829,
          "y" : 1004
        },
        "radius" : 28
      },
      "verseRef" : {
        "chapterNumber" : 12,
        "verseNumber" : 25
      }
    },
    {
      "position" : {
        "center" : {
          "x" : 796,
          "y" : 1235
        },
        "radius" : 28
      },
      "verseRef" : {
        "chapterNumber" : 12,
        "verseNumber" : 26
      }
    },
    {
      "position" : {
        "center" : {
          "x" : 690,
          "y" : 1351
        },
        "radius" : 28
      },
      "verseRef" : {
        "chapterNumber" : 12,
        "verseNumber" : 27
      }
    },
    {
      "position" : {
        "center" : {
          "x" : 422,
          "y" : 1467
        },
        "radius" : 28
      },
      "verseRef" : {
        "chapterNumber" : 12,
        "verseNumber" : 28
      }
    },
    {
      "position" : {
        "center" : {
          "x" : 69,
          "y" : 1583
        },
        "radius" : 28
      },
      "verseRef" : {
        "chapterNumber" : 12,
        "verseNumber" : 29
      }
    },
    {
      "position" : {
        "center" : {
          "x" : 70,
          "y" : 1814
        },
        "radius" : 28
      },
      "verseRef" : {
        "chapterNumber" : 12,
        "verseNumber" : 30
      }
    }
  ],
  "lines" : [
    {
      "start" : {
        "x" : 36,
        "y" : 137
      },
      "end" : {
        "x" : 1100,
        "y" : 253
      }
    },
    {
      "start" : {
        "x" : 36,
        "y" : 253
      },
      "end" : {
        "x" : 1100,
        "y" : 369
      }
    },
    {
      "start" : {
        "x" : 36,
        "y" : 369
      },
      "end" : {
        "x" : 1100,
        "y" : 485
      }
    },
    {
      "start" : {
        "x" : 36,
        "y" : 485
      },
      "end" : {
        "x" : 1100,
        "y" : 601
      }
    },
    {
      "start" : {
        "x" : 36,
        "y" : 601
      },
      "end" : {
        "x" : 1100,
        "y" : 717
      }
    },
    {
      "start" : {
        "x" : 36,
        "y" : 717
      },
      "end" : {
        "x" : 1100,
        "y" : 833
      }
    },
    {
      "start" : {
        "x" : 36,
        "y" : 833
      },
      "end" : {
        "x" : 1100,
        "y" : 949
      }
    },
    {
      "start" : {
        "x" : 36,
        "y" : 949
      },
      "end" : {
        "x" : 1100,
        "y" : 1065
      }
    },
    {
      "start" : {
        "x" : 36,
        "y" : 1065
      },
      "end" : {
        "x" : 1100,
        "y" : 1181
      }
    },
    {
      "start" : {
        "x" : 36,
        "y" : 1181
      },
      "end" : {
        "x" : 1100,
        "y" : 1297
      }
    },
    {
      "start" : {
        "x" : 36,
        "y" : 1297
      },
      "end" : {
        "x" : 1100,
        "y" : 1413
      }
    },
    {
      "start" : {
        "x" : 36,
        "y" : 1413
      },
      "end" : {
        "x" : 1100,
        "y" : 1529
      }
    },
    {
      "start" : {
        "x" : 36,
        "y" : 1529
      },
      "end" : {
        "x" : 1100,
        "y" : 1645
      }
    },
    {
      "start" : {
        "x" : 36,
        "y" : 1645
      },
      "end" : {
        "x" : 1100,
        "y" : 1761
      }
    },
    {
      "start" : {
        "x" : 36,
        "y" : 1761
      },
      "end" : {
        "x" : 1100,
        "y" : 1874
      }
    }
  ],
  "headers" : [ ],
  "basmallah" : [ ]
}